qg_common_sdk/Cal.py
qg_common_sdk/Mongodb.py
qg_common_sdk/RedisConnect.py
qg_common_sdk/__init__.py
qg_common_sdk/catchException.py
qg_common_sdk/dataBaseConnectService.py
qg_common_sdk/dateTool.py
qg_common_sdk/dictApi.py
qg_common_sdk/dictOpr.py
qg_common_sdk/excelToDeal.py
qg_common_sdk/headerResolve.py
qg_common_sdk/log.py
qg_common_sdk/operUserInfo.py
qg_common_sdk/returnInfo.py
qg_common_sdk/routers.py
qg_common_sdk/sysTool.py
qg_common_sdk/verifyCode.py
qg_common_sdk/dist1/CalLexer.py
qg_common_sdk/dist1/CalListener.py
qg_common_sdk/dist1/CalParser.py
qg_common_sdk/dist1/CalVisitor.py
qg_common_sdk/dist1/CalculateLexer.py
qg_common_sdk/dist1/__init__.py
qg_common_sdk-1.2.1.dist-info/METADATA
qg_common_sdk-1.2.1.dist-info/WHEEL
qg_common_sdk-1.2.1.dist-info/top_level.txt
qg_common_sdk-1.2.1.dist-info/RECORD
