Metadata-Version: 2.1
Name: qg-common-sdk
Version: 1.2.1
Summary: 全高python统一处理底层框架封装包
Home-page: http://192.168.117.144/cetc28/spiderStructFrameWork
Author: lbb
Author-email: liubeibei15895926598@gmail.com
Maintainer: lbb
Maintainer-email: liubeibei15895926598@gmail.com
License: GPL3 License
Platform: all
Classifier: Development Status :: 4 - Beta
Classifier: Operating System :: OS Independent
Classifier: Intended Audience :: Developers
Classifier: Programming Language :: Python
Classifier: Programming Language :: Python :: Implementation
Classifier: Programming Language :: Python :: 3
Classifier: Programming Language :: Python :: 3.4
Classifier: Programming Language :: Python :: 3.5
Classifier: Programming Language :: Python :: 3.5
Classifier: Programming Language :: Python :: 3.6
Classifier: Programming Language :: Python :: 3.7
Classifier: Topic :: Software Development :: Libraries
Requires-Dist: python-logstash (>=0.4.6)
Requires-Dist: redis (>=3.5.3)
Requires-Dist: termcolor (>=1.1.0)
Requires-Dist: xlrd (>=1.2.0)
Requires-Dist: openpyxl (>=3.0.5)
Requires-Dist: Django (>=3.1.7)
Requires-Dist: pymongo (>=3.11.3)
Requires-Dist: pipreqs (>=0.4.10)
Requires-Dist: colorama (>=0.4.4)
Requires-Dist: py-bootstrap (>=0.0.12)
